LICENSE
README.md
setup.py
blueye/__init__.py
blueye/example.py
blueye.egg-info/PKG-INFO
blueye.egg-info/SOURCES.txt
blueye.egg-info/dependency_links.txt
blueye.egg-info/top_level.txt
tests/__init__.py