Metadata-Version: 2.1
Name: blueye
Version: 0.0.0
Summary: Underwater Visual Perception
Author: Proneet Sharma
Author-email: proneet.shartma@dfki.de
Classifier: Programming Language :: Python :: 3
Classifier: License :: OSI Approved :: MIT License
Classifier: Operating System :: OS Independent
Requires-Python: >=3.8
License-File: LICENSE
